[
    {
        "author": "Pete Hunt",
        "text": "This is one comment"
    },
    {
        "author": "Jordan Walke",
        "text": "This is *another* comment"
    },
    {
        "author": "John Doe",
        "text": "This is *yet another* comment"
    },
    {
        "author": "Potato Head",
        "text": "Potatos Potate"
    },
    {
        "id": 1450097792775,
        "author": "asda",
        "text": "sdff"
    },
    {
        "id": 1450097927604,
        "author": "sdfsddf",
        "text": "sdfdf"
    }
]